gossip/__init__.py
gossip/_gossip.cpython-310-x86_64-linux-gnu.so
gossip/pss_manager.py
gossip/simulation.py
gossip/stats.py
gossipsampling-0.1.3.dist-info/LICENSE.txt
gossipsampling-0.1.3.dist-info/METADATA
gossipsampling-0.1.3.dist-info/WHEEL
gossipsampling-0.1.3.dist-info/top_level.txt
gossipsampling-0.1.3.dist-info/RECORD
