Metadata-Version: 2.1
Name: gossipsampling
Version: 0.1.3
Summary: C++ Gossip Peer Sampling Service with Python Front End
Home-page: https://github.com/matthew-alexander-love/gossip
Author: Matthew Love
Author-email: gossipsampling@gmail.com
License: UNKNOWN
Platform: UNKNOWN
License-File: LICENSE.txt
